django_dramatiq_result_backend/__init__.py
django_dramatiq_result_backend/admin.py
django_dramatiq_result_backend/apps.py
django_dramatiq_result_backend/backends.py
django_dramatiq_result_backend/models.py
django_dramatiq_result_backend/setup.py
django_dramatiq_result_backend/migrations/0001_initial.py
django_dramatiq_result_backend/migrations/__init__.py
django_dramatiq_result_backend-0.1.5.dist-info/METADATA
django_dramatiq_result_backend-0.1.5.dist-info/WHEEL
django_dramatiq_result_backend-0.1.5.dist-info/top_level.txt
django_dramatiq_result_backend-0.1.5.dist-info/RECORD
