Metadata-Version: 2.1
Name: django-dramatiq-result-backend
Version: 0.1.5
Summary: A Django-based result backend for Dramatiq.
Author-email: Sunil <shrest4647+pip@gmail.com>
License: MIT License
Project-URL: Homepage, https://github.com/Shrest4647/django-dramatiq-result-backend
Project-URL: Documentation, https://github.com/Shrest4647/django-dramatiq-result-backend#readme
Project-URL: Source Code, https://github.com/Shrest4647/django-dramatiq-result-backend
Project-URL: Bug Tracker, https://github.com/Shrest4647/django-dramatiq-result-backend/issues
Keywords: django,dramatiq,result-backend,async
Classifier: Framework :: Django
Classifier: Intended Audience :: Developers
Classifier: Programming Language :: Python :: 3
Requires-Python: >=3.7
Requires-Dist: django>=3.2
Requires-Dist: dramatiq>=1.2
Provides-Extra: dev
Requires-Dist: pytest>=7.1; extra == "dev"
Requires-Dist: pytest-cov>=3.0; extra == "dev"
Requires-Dist: pytest-django>=4.5; extra == "dev"
